openaidantic/__init__.py
openaidantic/agent.py
openaidantic/api.py
openaidantic/costs.py
openaidantic/functions.py
openaidantic/helpers.py
openaidantic/lib/__init__.py
openaidantic/lib/client.py
openaidantic/lib/memory.py
openaidantic/lib/utils.py
openaidantic/lib/vector.py
openaidantic/schema.py
openaidantic/templating.py
openaidantic/typedefs.py
openaidantic-0.1.6.dist-info/METADATA
openaidantic-0.1.6.dist-info/WHEEL
openaidantic-0.1.6.dist-info/RECORD
