Metadata-Version: 2.1
Name: openaidantic
Version: 0.1.6
Summary: A fully typed user friendly openai wrapper package
Author: Oscar Bahamonde
Author-email: oscar.bahamonde.dev@gmail.com
Requires-Python: >=3.10,<4.0
Classifier: Programming Language :: Python :: 3
Classifier: Programming Language :: Python :: 3.10
Classifier: Programming Language :: Python :: 3.11
Requires-Dist: jinja2 (>=3.1.2,<4.0.0)
Requires-Dist: openai (>=0.28.1,<0.29.0)
Requires-Dist: pydantic (==1.10.12)
Requires-Dist: pydub (>=0.25.1,<0.26.0)
Requires-Dist: rich (>=13.6.0,<14.0.0)
Requires-Dist: tenacity (>=8.2.3,<9.0.0)
Requires-Dist: tiktoken (>=0.5.1,<0.6.0)
